rdbunit/__init__.py
rdbunit/__main__.py
rdbunit-1.1.4.dist-info/METADATA
rdbunit-1.1.4.dist-info/WHEEL
rdbunit-1.1.4.dist-info/entry_points.txt
rdbunit-1.1.4.dist-info/licenses/LICENSE
rdbunit-1.1.4.dist-info/RECORD
