Metadata-Version: 2.1
Name: rdbunit
Version: 1.1.4
Summary: RDBUnit is a unit testing framework for relational database queries.
Project-URL: Homepage, https://github.com/dspinellis/rdbunit
Project-URL: Documentation, https://github.com/dspinellis/rdbunit
Project-URL: Repository, https://github.com/dspinellis/rdbunit.git
Project-URL: Bug Tracker, https://github.com/dspinellis/rdbunit/issues
Author-email: Diomidis Spinellis <dds@aueb.gr>
License: 
License-File: LICENSE
Keywords: PostgreSQL,SQL,SQLite,mySQL,unit testing
Classifier: Development Status :: 5 - Production/Stable
Classifier: Environment :: Console
Classifier: Intended Audience :: Developers
Classifier: License :: OSI Approved :: Apache Software License
Classifier: Operating System :: MacOS
Classifier: Operating System :: Microsoft :: Windows
Classifier: Operating System :: POSIX
Classifier: Operating System :: Unix
Classifier: Programming Language :: Python
Classifier: Programming Language :: Python :: 3
Classifier: Topic :: Software Development :: Testing :: Unit
Requires-Python: >=3.7
